<?xml version='1.0' encoding='utf-8'?>
<TextureAtlas imagePath="insane_turned.png"><SubTexture name="insane-turned idle dance0000" x="738" y="0" width="218" height="209" frameX="-351" frameY="-180" frameWidth="824" frameHeight="626" />
<SubTexture name="insane-turned idle dance0001" x="738" y="0" width="218" height="209" frameX="-351" frameY="-180" frameWidth="824" frameHeight="626" />
<SubTexture name="insane-turned idle dance0002" x="0" y="670" width="219" height="208" frameX="-348" frameY="-180" frameWidth="824" frameHeight="626" />
<SubTexture name="insane-turned idle dance0003" x="0" y="670" width="219" height="208" frameX="-348" frameY="-180" frameWidth="824" frameHeight="626" />
<SubTexture name="insane-turned idle dance0004" x="219" y="670" width="220" height="207" frameX="-346" frameY="-180" frameWidth="824" frameHeight="626" />
<SubTexture name="insane-turned idle dance0005" x="219" y="670" width="220" height="207" frameX="-346" frameY="-180" frameWidth="824" frameHeight="626" />
<SubTexture name="insane-turned idle dance0006" x="439" y="670" width="221" height="204" frameX="-341" frameY="-180" frameWidth="824" frameHeight="626" />
<SubTexture name="insane-turned idle dance0007" x="439" y="670" width="221" height="204" frameX="-341" frameY="-180" frameWidth="824" frameHeight="626" />
<SubTexture name="insane-turned idle dance0008" x="661" y="670" width="222" height="204" frameX="-340" frameY="-180" frameWidth="824" frameHeight="626" />
<SubTexture name="insane-turned idle dance0009" x="661" y="670" width="222" height="204" frameX="-340" frameY="-180" frameWidth="824" frameHeight="626" />
<SubTexture name="insane-turned right note0000" x="0" y="0" width="180" height="235" frameX="-343" frameY="-180" frameWidth="824" frameHeight="626" />
<SubTexture name="insane-turned right note0001" x="0" y="0" width="180" height="235" frameX="-343" frameY="-180" frameWidth="824" frameHeight="626" />
<SubTexture name="insane-turned right note0002" x="180" y="0" width="177" height="234" frameX="-340" frameY="-180" frameWidth="824" frameHeight="626" />
<SubTexture name="insane-turned right note0003" x="180" y="0" width="177" height="234" frameX="-340" frameY="-180" frameWidth="824" frameHeight="626" />
<SubTexture name="insane-turned right note0004" x="358" y="0" width="176" height="233" frameX="-335" frameY="-180" frameWidth="824" frameHeight="626" />
<SubTexture name="insane-turned up note0000" x="0" y="235" width="209" height="221" frameX="-334" frameY="-180" frameWidth="824" frameHeight="626" />
<SubTexture name="insane-turned up note0001" x="0" y="235" width="209" height="221" frameX="-334" frameY="-180" frameWidth="824" frameHeight="626" />
<SubTexture name="insane-turned up note0002" x="534" y="0" width="204" height="214" frameX="-339" frameY="-180" frameWidth="824" frameHeight="626" />
<SubTexture name="insane-turned up note0003" x="534" y="0" width="204" height="214" frameX="-339" frameY="-180" frameWidth="824" frameHeight="626" />
<SubTexture name="insane-turned up note0004" x="398" y="456" width="198" height="210" frameX="-343" frameY="-180" frameWidth="824" frameHeight="626" />
<SubTexture name="insane_turned down note0000" x="738" y="209" width="176" height="209" frameX="-344" frameY="-184" frameWidth="824" frameHeight="626" />
<SubTexture name="insane_turned down note0001" x="738" y="209" width="176" height="209" frameX="-344" frameY="-184" frameWidth="824" frameHeight="626" />
<SubTexture name="insane_turned down note0002" x="534" y="214" width="176" height="212" frameX="-339" frameY="-180" frameWidth="824" frameHeight="626" />
<SubTexture name="insane_turned down note0003" x="534" y="214" width="176" height="212" frameX="-339" frameY="-180" frameWidth="824" frameHeight="626" />
<SubTexture name="insane_turned down note0004" x="222" y="456" width="176" height="212" frameX="-335" frameY="-180" frameWidth="824" frameHeight="626" />
<SubTexture name="insane_turned left note0000" x="222" y="1076" width="248" height="175" frameX="-329" frameY="-181" frameWidth="824" frameHeight="626" />
<SubTexture name="insane_turned left note0001" x="222" y="1076" width="248" height="175" frameX="-329" frameY="-181" frameWidth="824" frameHeight="626" />
<SubTexture name="insane_turned left note0002" x="934" y="1076" width="254" height="175" frameX="-334" frameY="-181" frameWidth="824" frameHeight="626" />
<SubTexture name="insane_turned left note0003" x="934" y="1076" width="254" height="175" frameX="-334" frameY="-181" frameWidth="824" frameHeight="626" />
<SubTexture name="insane_turned left note0004" x="1403" y="0" width="252" height="175" frameX="-340" frameY="-180" frameWidth="824" frameHeight="626" />
<SubTexture name="insane_turned what0000" x="1403" y="175" width="222" height="175" frameX="-340" frameY="-180" frameWidth="824" frameHeight="626" />
<SubTexture name="insane_turned what0001" x="738" y="418" width="215" height="175" frameX="-341" frameY="-182" frameWidth="824" frameHeight="626" />
<SubTexture name="insane_turned what0002" x="883" y="878" width="240" height="178" frameX="-331" frameY="-171" frameWidth="824" frameHeight="626" />
<SubTexture name="insane_turned what0003" x="471" y="1076" width="234" height="175" frameX="-333" frameY="-175" frameWidth="824" frameHeight="626" />
<SubTexture name="insane_turned what0004" x="705" y="1076" width="228" height="175" frameX="-335" frameY="-177" frameWidth="824" frameHeight="626" />
<SubTexture name="insane_turned what0005" x="1181" y="0" width="221" height="175" frameX="-338" frameY="-179" frameWidth="824" frameHeight="626" />
<SubTexture name="insane_turned what0006" x="0" y="1076" width="222" height="175" frameX="-338" frameY="-179" frameWidth="824" frameHeight="626" />
<SubTexture name="insane_turned what0007" x="209" y="235" width="221" height="221" frameX="-338" frameY="-179" frameWidth="824" frameHeight="626" />
<SubTexture name="insane_turned what0008" x="0" y="878" width="221" height="198" frameX="-338" frameY="-179" frameWidth="824" frameHeight="626" />
<SubTexture name="insane_turned what0009" x="664" y="878" width="219" height="182" frameX="-338" frameY="-180" frameWidth="824" frameHeight="626" />
<SubTexture name="insane_turned what0010" x="443" y="878" width="221" height="184" frameX="-338" frameY="-180" frameWidth="824" frameHeight="626" />
<SubTexture name="insane_turned what0011" x="957" y="0" width="224" height="201" frameX="-353" frameY="-188" frameWidth="824" frameHeight="626" />
<SubTexture name="insane_turned what0012" x="221" y="878" width="221" height="196" frameX="-350" frameY="-188" frameWidth="824" frameHeight="626" />
<SubTexture name="insane_turned what0013" x="957" y="600" width="220" height="198" frameX="-348" frameY="-188" frameWidth="824" frameHeight="626" />
<SubTexture name="insane_turned what0014" x="957" y="401" width="220" height="199" frameX="-343" frameY="-184" frameWidth="824" frameHeight="626" />
<SubTexture name="insane_turned what0015" x="957" y="201" width="219" height="200" frameX="-340" frameY="-181" frameWidth="824" frameHeight="626" />
<SubTexture name="insane_turned miss0000" x="0" y="456" width="222" height="213" frameX="-340" frameY="-171" frameWidth="824" frameHeight="626" />
</TextureAtlas>