{
	"animations": [
		{
			"offsets": [
				0,
				0
			],
			"cameraOffset": [
				0,
				0
			],
			"loop": false,
			"fps": 24,
			"anim": "idle",
			"indices": [],
			"name": "idle0"
		},
		{
			"offsets": [
				0,
				0
			],
			"cameraOffset": [
				0,
				30
			],
			"loop": false,
			"fps": 24,
			"anim": "singDOWN",
			"indices": [],
			"name": "down0"
		},
		{
			"offsets": [
				0,
				0
			],
			"cameraOffset": [
				0,
				-30
			],
			"loop": false,
			"fps": 24,
			"anim": "singUP",
			"indices": [],
			"name": "up0"
		},
		{
			"offsets": [
				0,
				0
			],
			"cameraOffset": [
				0,
				0
			],
			"loop": false,
			"fps": 24,
			"anim": "idle-tweak",
			"indices": [],
			"name": "idle-tweak0"
		},
		{
			"offsets": [
				0,
				0
			],
			"cameraOffset": [
				-30,
				0
			],
			"loop": false,
			"fps": 24,
			"anim": "singLEFT-tweak",
			"indices": [],
			"name": "left-tweak0"
		},
		{
			"offsets": [
				0,
				0
			],
			"cameraOffset": [
				0,
				30
			],
			"loop": false,
			"fps": 24,
			"anim": "singDOWN-tweak",
			"indices": [],
			"name": "down-tweak0"
		},
		{
			"offsets": [
				0,
				0
			],
			"cameraOffset": [
				0,
				-30
			],
			"loop": false,
			"fps": 24,
			"anim": "singUP-tweak",
			"indices": [],
			"name": "up-tweak0"
		},
		{
			"offsets": [
				0,
				0
			],
			"cameraOffset": [
				30,
				0
			],
			"loop": false,
			"fps": 24,
			"anim": "singRIGHT-tweak",
			"indices": [],
			"name": "right-tweak0"
		},
		{
			"loop": false,
			"cameraOffset": [
				0,
				0
			],
			"offsets": [
				0,
				0
			],
			"anim": "idle-scream",
			"fps": 24,
			"name": "idle-scream0",
			"indices": []
		},
		{
			"loop": false,
			"cameraOffset": [
				-30,
				0
			],
			"offsets": [
				0,
				0
			],
			"anim": "singLEFT-scream",
			"fps": 24,
			"name": "left-scream0",
			"indices": []
		},
		{
			"offsets": [
				0,
				0
			],
			"cameraOffset": [
				0,
				30
			],
			"loop": false,
			"fps": 24,
			"anim": "singDOWN-scream",
			"indices": [],
			"name": "down-scream0"
		},
		{
			"offsets": [
				0,
				0
			],
			"cameraOffset": [
				0,
				-30
			],
			"loop": false,
			"fps": 24,
			"anim": "singUP-scream",
			"indices": [],
			"name": "up-scream0"
		},
		{
			"offsets": [
				0,
				0
			],
			"cameraOffset": [
				30,
				0
			],
			"loop": false,
			"fps": 24,
			"anim": "singRIGHT-scream",
			"indices": [],
			"name": "right-scream0"
		},
		{
			"offsets": [
				0,
				0
			],
			"indices": [],
			"fps": 24,
			"anim": "singRIGHT",
			"loop": false,
			"name": "left0"
		},
		{
			"offsets": [
				0,
				0
			],
			"indices": [],
			"fps": 24,
			"anim": "singLEFT",
			"loop": false,
			"name": "right0"
		}
	],
	"vocals_file": "",
	"no_antialiasing": false,
	"image": "characters/teto",
	"position": [
		-420,
		240
	],
	"healthicon": "teto",
	"flip_x": true,
	"healthbar_colors": [
		255,
		0,
		66
	],
	"camera_position": [
		60,
		-40
	],
	"sing_duration": 4,
	"scale": 1.5,
	"_editor_isPlayer": false
}